{
    "Supreme Council for Islamic Revolution in Iraq (SCIRI)": {
        "B": 5.0, 
        "W": [
            0.0, 
            0.0, 
            0.0, 
            0.044189524586808984, 
            0.0, 
            0.08209437336778817, 
            0.0, 
            0.0, 
            0.010781296248339506, 
            0.046086848168347926, 
            0.0, 
            0.0, 
            0.0, 
            0.0, 
            0.0, 
            0.0, 
            0.04471536394834489, 
            0.11300011703058126, 
            0.0, 
            0.0, 
            0.0, 
            0.0, 
            0.0, 
            0.0, 
            0.0, 
            0.0, 
            0.16685520629928807, 
            0.0, 
            0.0, 
            0.0
        ], 
        "lambda": 0.001120950697347153
    }, 
    "Omar Bin Khattab Group": {
        "B": 5.0, 
        "W": [
            0.0, 
            0.0, 
            0.0, 
            0.0, 
            0.0, 
            0.0, 
            0.0, 
            0.0, 
            0.0, 
            0.0, 
            0.0, 
            0.0, 
            0.02470570859992093, 
            0.0, 
            0.05341183644794456, 
            0.0, 
            0.0, 
            0.054236902249169466, 
            0.019347715275781822, 
            0.0, 
            0.0, 
            0.0, 
            0.0, 
            0.0, 
            0.0, 
            0.0, 
            0.0, 
            0.027252076315410562, 
            0.0, 
            0.0
        ], 
        "lambda": 0.0013897856478864408
    }, 
    "Mujahedeen Brigades": {
        "B": 5.0, 
        "W": [
            0.0, 
            0.0, 
            0.0, 
            0.44320072997399806, 
            0.10421625224054952, 
            0.01501928126329859, 
            0.0, 
            0.0, 
            0.0, 
            0.0, 
            0.0, 
            0.0, 
            0.0, 
            0.0, 
            0.0, 
            0.011428994992048394, 
            0.0, 
            0.0, 
            0.0, 
            0.0, 
            0.0, 
            0.0, 
            0.0, 
            0.0, 
            0.0, 
            0.0, 
            0.0, 
            0.0, 
            0.0, 
            0.0
        ], 
        "lambda": 0.001908680301107623
    }, 
    "Imam Hussein Brigade": {
        "B": 5.0, 
        "W": [
            0.020602433540897237, 
            0.19622183110680366, 
            0.11969011448030688, 
            0.0, 
            0.0, 
            0.0, 
            0.0, 
            0.0, 
            0.0, 
            0.0, 
            0.0, 
            0.011120785365803514, 
            0.08719336216377904, 
            0.02148973595730988, 
            0.0, 
            0.0, 
            0.0, 
            0.0, 
            0.0, 
            0.0, 
            0.0, 
            0.027215372896915564, 
            0.0, 
            0.010950561854179265, 
            0.0, 
            0.0, 
            0.0, 
            0.0, 
            0.0, 
            0.0
        ], 
        "lambda": 0.0013490289639967715
    }, 
    "Ansar al-Islam": {
        "B": 5.0, 
        "W": [
            0.0, 
            0.0, 
            0.0, 
            0.0, 
            0.0, 
            0.0, 
            0.0, 
            0.0, 
            0.0, 
            0.023763020824348155, 
            0.0, 
            0.0, 
            0.13224665594933363, 
            0.0, 
            0.0, 
            0.09297076184519193, 
            0.00225939961547997, 
            0.0, 
            0.0, 
            0.02679009366403845, 
            0.0, 
            0.0, 
            0.0, 
            0.012833050687992216, 
            0.02321808971488977, 
            0.0, 
            0.06577829856519299, 
            0.00398240435812677, 
            0.0, 
            0.0
        ], 
        "lambda": 0.002902516206761413
    }, 
    "Mujahedeen Shura Council": {
        "B": 5.0, 
        "W": [
            0.0, 
            0.0, 
            0.0, 
            0.0, 
            0.0, 
            0.018870115249596715, 
            0.0, 
            0.0, 
            0.0, 
            0.0, 
            0.0, 
            0.0, 
            0.0, 
            0.044627738507184565, 
            0.0, 
            0.0, 
            0.024505439339606368, 
            0.0, 
            0.0, 
            0.0, 
            0.002267796815333524, 
            0.0, 
            0.0, 
            0.0, 
            0.0028687241378769776, 
            0.01503883066021095, 
            0.030261456582848595, 
            0.0, 
            0.0, 
            0.0
        ], 
        "lambda": 0.0007646947010078063
    }, 
    "Takfir wal-Hijra (Excommunication and Exodus)": {
        "B": 5.0, 
        "W": [
            0.0, 
            0.0, 
            0.0, 
            0.0017099852859981046, 
            0.05088596145874329, 
            0.06980976503447862, 
            0.0, 
            0.0, 
            0.0, 
            0.0, 
            0.0, 
            0.004730999302612819, 
            0.026400449233572095, 
            0.0, 
            0.0, 
            0.054972949120310186, 
            0.0, 
            0.0, 
            0.0, 
            0.0, 
            0.0, 
            0.0, 
            0.043910716902232444, 
            0.0, 
            0.0, 
            0.0, 
            0.0, 
            0.019493417346352786, 
            0.0, 
            0.056104964557687174
        ], 
        "lambda": 0.001011830320937816
    }, 
    "Badr Brigades": {
        "B": 5.0, 
        "W": [
            0.0, 
            0.0, 
            0.0, 
            0.0, 
            0.0, 
            0.0, 
            0.0, 
            0.0, 
            0.0, 
            0.0, 
            0.0, 
            0.0, 
            0.03308184720396353, 
            0.0, 
            0.0, 
            0.0, 
            0.0, 
            0.0, 
            0.0, 
            0.0, 
            0.0, 
            0.0, 
            0.0, 
            0.0, 
            0.0441698130321689, 
            0.0, 
            0.0, 
            0.0, 
            0.0, 
            0.0
        ], 
        "lambda": 0.00030310356556053497
    }, 
    "Protectors of Islam Brigade": {
        "B": 5.0, 
        "W": [
            0.016580522307953257, 
            0.030242981285893547, 
            0.025746951309059917, 
            0.1675349540687053, 
            0.16573906298803126, 
            0.07390884811676308, 
            0.0, 
            0.0, 
            0.0, 
            0.02637253085371977, 
            0.0, 
            0.0, 
            0.00596767215570728, 
            0.0, 
            0.0, 
            0.0, 
            0.0, 
            0.0, 
            0.0, 
            0.0, 
            0.0, 
            0.0, 
            0.03286347016329922, 
            0.08689448567954192, 
            0.11948488129532171, 
            0.0, 
            0.0, 
            0.0, 
            0.0, 
            0.20492960134865584
        ], 
        "lambda": 0.0005310072133508032
    }, 
    "Khalid ibn Walid Brigade": {
        "B": 5.0, 
        "W": [
            0.0, 
            0.0, 
            0.0, 
            0.0, 
            0.0, 
            0.0, 
            0.0, 
            0.0, 
            0.0, 
            0.0, 
            0.0, 
            0.0, 
            0.0, 
            0.0, 
            0.0, 
            0.0, 
            0.0, 
            0.0, 
            0.06364588736599315, 
            0.0, 
            0.0, 
            0.05999187996466059, 
            0.034783516471482076, 
            0.0, 
            0.0, 
            0.0, 
            0.046469854054853856, 
            0.0, 
            0.0, 
            0.0
        ], 
        "lambda": 0.0007590455858313494
    }, 
    "Jaish al-Ta'ifa al-Mansura": {
        "B": 5.0, 
        "W": [
            0.0, 
            0.0, 
            0.0, 
            0.0, 
            0.0, 
            0.0, 
            0.0, 
            0.004173867841140855, 
            0.13529158984741024, 
            0.0, 
            0.0, 
            0.0, 
            0.0, 
            0.0, 
            0.0, 
            0.0, 
            0.0, 
            0.10759268570866955, 
            0.0, 
            0.0602309629685636, 
            0.0, 
            0.034953943257049244, 
            0.0, 
            0.0, 
            0.0, 
            0.0, 
            0.0, 
            0.0, 
            0.0, 
            0.0
        ], 
        "lambda": 0.0032023864130831985
    }, 
    "Al Zawahiri Loyalists": {
        "B": 5.0, 
        "W": [
            0.0, 
            0.0, 
            0.0, 
            0.005419149761177095, 
            0.00640558470209027, 
            0.012235651756980815, 
            0.013701443550415436, 
            0.004133501229699261, 
            0.02063877328055702, 
            0.0, 
            0.055724035067136364, 
            0.0, 
            0.0, 
            0.0, 
            0.10778425692071195, 
            0.0, 
            0.0, 
            0.0, 
            0.030708808218995957, 
            0.003494827852491708, 
            0.0, 
            0.28043686858854955, 
            0.0, 
            0.0, 
            0.0, 
            0.0, 
            0.0, 
            0.0, 
            0.0, 
            0.0
        ], 
        "lambda": 0.0014591776173218018
    }, 
    "Mujahedeen Corps in Iraq": {
        "B": 5.0, 
        "W": [
            0.000860942008257786, 
            0.02541154642052999, 
            0.06308527761760813, 
            0.0, 
            0.0, 
            0.0, 
            0.0, 
            0.0, 
            0.0, 
            0.0, 
            0.0286749229588045, 
            0.029679329011076973, 
            0.19132817290245333, 
            0.0, 
            0.0, 
            0.0, 
            0.0, 
            0.0, 
            0.0, 
            0.0, 
            0.0, 
            0.004952437647273864, 
            0.0, 
            0.0, 
            0.12488954210845234, 
            0.0, 
            0.0, 
            0.0, 
            0.0, 
            0.0
        ], 
        "lambda": 0.0012834124985301515
    }, 
    "Junaid Jihadist Battalion": {
        "B": 5.0, 
        "W": [
            0.0, 
            0.0, 
            0.0, 
            0.008724367879808593, 
            0.006983659006054966, 
            0.008979930952560077, 
            0.055952290737559474, 
            0.13706895078496945, 
            0.08179902644160858, 
            0.06714282463484016, 
            0.0, 
            0.0, 
            0.024728422125492432, 
            0.0, 
            0.0, 
            0.0, 
            0.0, 
            0.0, 
            0.0, 
            0.0843799563942223, 
            0.0, 
            0.0, 
            0.0, 
            0.03305267968281961, 
            0.0, 
            0.0, 
            0.046663653817886924, 
            0.0, 
            0.08551109886370932, 
            0.0
        ], 
        "lambda": 0.0001344861625514169
    }, 
    "AQI": {
        "B": 5.0, 
        "W": [
            0.0, 
            0.9050975344790747, 
            0.0, 
            0.017253328804629778, 
            0.0, 
            0.0159556734420005, 
            0.0, 
            0.11044578569507409, 
            0.0, 
            0.0, 
            0.0, 
            0.0, 
            0.0, 
            0.0, 
            0.0, 
            0.0, 
            0.0, 
            0.0, 
            0.0, 
            0.0, 
            0.0, 
            0.0, 
            0.0, 
            0.0, 
            0.0, 
            0.0, 
            0.0, 
            0.0, 
            0.0, 
            0.0
        ], 
        "lambda": 0.0016602903070998072
    }, 
    "Mujahedeen Group": {
        "B": 5.0, 
        "W": [
            0.04754371001088098, 
            0.015170857811980656, 
            0.049819969539128824, 
            0.00959973700872914, 
            0.002752866036417502, 
            0.08531212886790682, 
            0.0, 
            0.0, 
            0.0, 
            0.0, 
            0.0, 
            0.0, 
            0.032171722549639764, 
            0.0, 
            0.0, 
            0.11855198232265712, 
            0.0, 
            0.0, 
            0.0, 
            0.0, 
            0.0, 
            0.0, 
            0.0, 
            0.0, 
            0.0, 
            0.08554677850163298, 
            0.0, 
            0.027670488269091104, 
            0.0, 
            0.033451517498446874
        ], 
        "lambda": 0.0016448285495331268
    }, 
    "Holders of the Black Banners": {
        "B": 5.0, 
        "W": [
            0.0, 
            0.0, 
            0.0, 
            0.0, 
            0.0, 
            0.0, 
            0.26946774242060145, 
            0.07720278206777059, 
            0.04821734571335559, 
            0.0, 
            0.0, 
            0.0, 
            0.0, 
            0.0, 
            0.02906084062679791, 
            0.0, 
            0.0, 
            0.0, 
            0.0, 
            0.02052766210389411, 
            0.0, 
            0.0, 
            0.0, 
            0.0, 
            0.0, 
            0.026191397751239617, 
            0.0, 
            0.0, 
            0.0, 
            0.0
        ], 
        "lambda": 0.0002604702638048924
    }, 
    "Brigades of Iman Hassan-al-Basri": {
        "B": 5.0, 
        "W": [
            0.0, 
            0.0, 
            0.0, 
            0.0, 
            0.0, 
            0.0, 
            0.0, 
            0.0, 
            0.0, 
            0.0, 
            0.0025850068418379383, 
            0.0, 
            0.0, 
            0.0, 
            0.0, 
            0.04310410993910749, 
            0.0, 
            0.0022911598152997805, 
            0.0, 
            0.0, 
            0.08201997599146049, 
            0.0, 
            0.10014339429267335, 
            0.12602861381429836, 
            0.0, 
            0.0, 
            0.042161121790972526, 
            0.0, 
            0.0, 
            0.0
        ], 
        "lambda": 0.0010634360297060508
    }, 
    "Armed Vanguards of a Second Mohammed Army": {
        "B": 5.0, 
        "W": [
            0.0, 
            0.0, 
            0.0, 
            0.0, 
            0.0, 
            0.0, 
            0.1666962711338747, 
            0.04661989370986795, 
            0.014130616680846522, 
            0.0, 
            0.0, 
            0.0, 
            0.017403391876960352, 
            0.0, 
            0.0, 
            0.0, 
            0.0, 
            0.0, 
            0.0, 
            0.0, 
            0.0, 
            0.0, 
            0.0, 
            0.0, 
            0.0, 
            0.0, 
            0.0, 
            0.008308370689307558, 
            0.0, 
            0.0
        ], 
        "lambda": 0.0013659938438086562
    }, 
    "Islamic Jihad Brigades": {
        "B": 5.0, 
        "W": [
            0.0, 
            0.0, 
            0.0, 
            0.0, 
            0.0, 
            0.0, 
            0.0, 
            0.0, 
            0.0, 
            0.0, 
            0.0, 
            0.0, 
            0.0, 
            0.0, 
            0.0, 
            0.05801921183558798, 
            0.0, 
            0.0, 
            0.0, 
            0.0, 
            0.0, 
            0.0, 
            0.0, 
            0.0, 
            0.0, 
            0.0, 
            0.0, 
            0.0, 
            0.0, 
            0.00953863098427794
        ], 
        "lambda": 0.0004597197480674545
    }, 
    "Islamic Movement of Iraqi Mujahidin": {
        "B": 5.0, 
        "W": [
            0.0, 
            0.0, 
            0.0, 
            0.0, 
            0.0, 
            0.0, 
            0.0, 
            0.0, 
            0.0, 
            0.0, 
            0.0, 
            0.0, 
            0.0, 
            0.0, 
            0.0, 
            0.0, 
            0.0, 
            0.26395184520612175, 
            0.0, 
            0.006905638330532085, 
            0.058448638325786784, 
            0.0, 
            0.0, 
            0.06131631615758201, 
            0.0, 
            0.0, 
            0.0, 
            0.04446695304894002, 
            0.03501688338078098, 
            0.0
        ], 
        "lambda": 0.0019510357628715288
    }, 
    "Ansar al-Jihad": {
        "B": 5.0, 
        "W": [
            0.10763320412834497, 
            0.010993420970264574, 
            0.05791915488828597, 
            0.0, 
            0.0, 
            0.0, 
            0.08470211541679461, 
            0.0633932818738753, 
            0.04693492605453539, 
            0.02505181788866795, 
            0.0, 
            0.0, 
            0.0, 
            0.03368317984162026, 
            0.0, 
            0.0, 
            0.0, 
            0.0, 
            0.06586477165738387, 
            0.0, 
            0.0, 
            0.0, 
            0.0, 
            0.0, 
            0.0, 
            0.0, 
            0.09306101705138754, 
            0.0, 
            0.0, 
            0.0
        ], 
        "lambda": 0.0008615325217589793
    }, 
    "Mahdi Army": {
        "B": 5.0, 
        "W": [
            0.0, 
            0.0, 
            0.0, 
            0.07445856051017923, 
            0.0, 
            0.09575309677250464, 
            0.0, 
            0.0, 
            0.0, 
            0.0, 
            0.0, 
            0.0, 
            0.0, 
            0.0, 
            0.0, 
            0.030094785307448024, 
            0.0, 
            0.0, 
            0.0, 
            0.0, 
            0.0, 
            0.0, 
            0.0, 
            0.0, 
            0.0, 
            0.0, 
            0.0, 
            0.0, 
            0.009857969848835704, 
            0.0
        ], 
        "lambda": 0.001136581869274714
    }, 
    "1920 Revolution Brigades": {
        "B": 5.0, 
        "W": [
            0.1532091039721897, 
            0.03535372894579556, 
            0.0, 
            0.0, 
            0.0, 
            0.0, 
            0.0, 
            0.0, 
            0.0, 
            0.0, 
            0.0, 
            0.00048011139445152843, 
            0.0, 
            0.0, 
            0.0766760133082186, 
            0.0, 
            0.0, 
            0.026446488969126335, 
            0.005068663557585618, 
            0.0, 
            0.07827966595479197, 
            0.0, 
            0.0, 
            0.0, 
            0.0, 
            0.0, 
            0.0, 
            0.0699872585037096, 
            0.0, 
            0.09272530653418866
        ], 
        "lambda": 0.0013824021620688794
    }, 
    "Ansar al-Sunna": {
        "B": 5.0, 
        "W": [
            0.0, 
            0.0, 
            0.0, 
            0.0, 
            0.0, 
            0.0, 
            0.0, 
            0.015399165914520126, 
            0.0, 
            0.01476062794280193, 
            0.0, 
            0.0, 
            0.12078101624911632, 
            0.0, 
            0.026854069241908203, 
            0.046158214164170625, 
            0.0, 
            0.0, 
            0.0, 
            0.0, 
            0.007280992434643006, 
            0.0, 
            0.0, 
            0.06602818293968186, 
            0.05181938704659509, 
            0.0, 
            0.0, 
            0.01237563891401329, 
            0.13747636045804307, 
            0.0
        ], 
        "lambda": 0.002419050468057503
    }, 
    "Mujahedeen Army": {
        "B": 5.0, 
        "W": [
            0.0, 
            0.0, 
            0.0, 
            0.0, 
            0.0, 
            0.0, 
            0.0, 
            0.0, 
            0.0, 
            0.0, 
            0.0, 
            0.0, 
            0.0, 
            0.0, 
            0.0, 
            0.011596025043945243, 
            0.007663478115796072, 
            0.05788722524697373, 
            0.13825443189513364, 
            0.0, 
            0.0, 
            0.0, 
            0.0, 
            0.0, 
            0.018914586781590314, 
            0.0, 
            0.0, 
            0.0, 
            0.0, 
            0.0
        ], 
        "lambda": 0.0016284058322939344
    }, 
    "Ansar al-Din": {
        "B": 5.0, 
        "W": [
            0.0, 
            0.0, 
            0.0, 
            0.03289274184784429, 
            0.04371711841637295, 
            0.05665458453149089, 
            0.019998624473019973, 
            0.024842624820773724, 
            0.023826008253825026, 
            0.0, 
            0.0, 
            0.0, 
            0.118856971419731, 
            0.0, 
            0.0, 
            0.007633033824671383, 
            0.10743150750419081, 
            0.03897008919638151, 
            0.0, 
            0.0, 
            0.0, 
            0.0, 
            0.0, 
            0.0, 
            0.0, 
            0.0, 
            0.0, 
            0.0, 
            0.0, 
            0.0
        ], 
        "lambda": 0.0022128131206793386
    }, 
    "Liberals of Galilee": {
        "B": 5.0, 
        "W": [
            0.0, 
            0.0, 
            0.0, 
            0.0, 
            0.0, 
            0.0, 
            0.0, 
            0.0, 
            0.0, 
            0.0, 
            0.0, 
            0.0, 
            0.037475830286331606, 
            0.0, 
            0.0, 
            0.0, 
            0.0, 
            0.0, 
            0.0, 
            0.0, 
            0.0, 
            0.0, 
            0.0, 
            0.0, 
            0.0, 
            0.0, 
            0.16531330231422875, 
            0.03624890926277495, 
            0.0, 
            0.0
        ], 
        "lambda": 0.0001897871974800131
    }, 
    "Abu Hafs al-Masri Brigades": {
        "B": 5.0, 
        "W": [
            0.0, 
            0.0, 
            0.0, 
            0.08421263860299648, 
            0.04960409993433875, 
            0.011781572144712761, 
            0.0, 
            0.0, 
            0.0, 
            0.0038269271613114914, 
            0.012451400557381712, 
            0.0, 
            0.0, 
            0.0, 
            0.029452310585318192, 
            0.0024121187509668633, 
            0.0, 
            0.0, 
            0.0, 
            0.06726541139284425, 
            0.07046042211331176, 
            0.06417586269260421, 
            0.10013636962571221, 
            0.10718600966865949, 
            0.0941238469528553, 
            0.0, 
            0.0, 
            0.01209963693062819, 
            0.018369809154382667, 
            0.0
        ], 
        "lambda": 0.0010599669076372497
    }, 
    "Islamic Army in Iraq (al-Jaish al-Islami fi al-Iraq)": {
        "B": 5.0, 
        "W": [
            0.04388937329862856, 
            0.1349015946181123, 
            0.014011806277663331, 
            0.0, 
            0.0, 
            0.0, 
            0.0, 
            0.0, 
            0.0, 
            0.11431941514988633, 
            0.0, 
            0.008729742456938087, 
            0.0, 
            0.0, 
            0.0, 
            0.0, 
            0.0, 
            0.0, 
            0.0, 
            0.0, 
            0.0, 
            0.10376028858799692, 
            0.0, 
            0.0, 
            0.0, 
            0.0, 
            0.053975643902126474, 
            0.0, 
            0.0, 
            0.36786221558868015
        ], 
        "lambda": 0.004859691244822082
    }
}